Workbook

Sheet LEEME
B1: MODELO DE PROYECCIÓN — SMART FOODS NUEVA ETAPA
B2: Borrador v1 · 19 jul 2026 · Todo SIN IVA · Moneda de reporte: ARS · Precios cargados en USD y convertidos por el TC de la hoja Parametros.
B3: Mes 1 = Septiembre 2026 (supuesto de arranque, sujeto al cierre societario). Horizonte: mensual Meses 1-24, anual Años 3-5.
B5: CÓMO USARLO
B6: 1. Celdas AZULES con fondo amarillo = inputs editables. Celdas negras = fórmulas (no tocar). Verdes = datos reales del histórico de SmartBrain.
B7: 2. Las 6 palancas principales: TC (Parametros!B2) · Ads por mes (Motor_D2C fila 3) · CAC (Supuestos!B4) · Puntos de venta (Motor_Dispro fila 3) · Sell-out por punto (Supuestos!B15) · Multiplicador de demanda (Parametros!B24).
B8: 3. Escenarios: Multiplicador de demanda = 0,70 (PISO) · 1,00 (BASE) · 1,30 (TECHO). Afecta órdenes orgánicas, clientes por ads y sell-out del canal.
B9: 4. La hoja Umbrales resume los semáforos: breakeven, recuperación del capital (piso 12 meses), tu umbral personal de USD 10k/mes y la tabla 3x/5x/10x de los socios.
B11: DATOS REALES USADOS (histórico Shopify en DB SmartBrain, 7.894 pedidos sep-2021 a jun-2026)
B12: AOV 2026: $107.788 ARS (2025: $90.078) → default del modelo: $110.000
B13: Recompra: 29% de los clientes compran 2+ veces · repetidores promedian 4 compras · 107 días promedio entre compras
B14: ~47% del volumen histórico de órdenes es recompra
... B25: EBITDA pre-impuestos (IIBB default 0%, editable en Parametros!B22). Aportes cash en 2 tramos: 50% mes 1, 50% mes 7 (editable).

Sheet Parametros
A1: PARÁMETROS GLOBALES
A2: Tipo de cambio ARS/USD | B2: 1500 | C2: Editable — mueve todo el modelo. Ref jul 2026.
A3: Mes 1 del modelo | B3: Septiembre 2026 | C3: Supuesto de arranque, sujeto al cierre societario.
A4: Sueldo fundador (USD/mes) | B4: 3000 | C4: Respuesta 25. Variable por objetivos NO incluida (definir aparte).
A5: CFO/admin fraccional (ARS/mes) | B5: 1000000 | C5: Respuesta 26.
A6: Contenido terciarizado (USD/mes) | B6: 1800 | C6: Draft 18/7 — todo terciarizado, sin equipo fijo.
A7: Contabilidad (ARS/mes) | B7: 400000 | C7: [SUPUESTO] a definir.
A8: Legales recurrentes (ARS/mes) | B8: 200000 | C8: [SUPUESTO] a definir.
A9: Seguros (ARS/mes) | B9: 150000 | C9: [SUPUESTO] a definir.
A10: Depósito tercero — fijo (ARS/mes) | B10: 250000 | C10: [SUPUESTO] "costo bajo fijo" (resp. 15).
A11: Tech / ecommerce (USD/mes) | B11: 300 | C11: Draft 18/7: 3.600/año. SmartBrain ya existe.
A12: Fulfillment variable (ARS/orden) | B12: 5000 | C12: [SUPUESTO] pick/pack depósito tercero, mayormente variable (resp. 15).
A13: Envío absorbido D2C (ARS/orden) | B13: 2500 | C13: [SUPUESTO] promedio si hay envío gratis sobre umbral. A definir (resp. 14).
A14: Comisión pasarela Shopify (%) | B14: 0.08 | C14: [SUPUESTO] MercadoPago AR. A definir (resp. 14).
A15: Comisión MercadoLibre (%) | B15: 0.15 | C15: [SUPUESTO] clásica + cargo. A definir.
... A30: In-kind PGN (USD, producción a costo) | B30: 67000 | C30: Resp. 30: producción inicial + reposiciones hasta completar el aporte.

Sheet Productos
A1: PRODUCTOS — PVP y costos en USD (editables) · conversión por TC
A2: SKU | B2: Fase | C2: Mes lanz. | D2: PVP USD | E2: Costo USD | F2: PVP ARS | G2: Costo ARS | H2: Mix D2C | I2: Mix Dispro
A3: Brain Boost — cápsulas x60 | B3: F1 | C3: 1 | D3: 35 | E3: 3.5 | F3: =D3*Parametros!$B$2 | G3: =E3*Parametros!$B$2 | H3: 0.14 | I3: 0.22
A4: Smart Calm — cápsulas x60 | B4: F1 | C4: 1 | D4: 35 | E4: 3.5 | F4: =D4*Parametros!$B$2 | G4: =E4*Parametros!$B$2 | H4: 0.12 | I4: 0.22
A5: Smart Glow — cápsulas x60 | B5: F1 | C5: 1 | D5: 35 | E5: 3.5 | F5: =D5*Parametros!$B$2 | G5: =E5*Parametros!$B$2 | H5: 0.08 | I5: 0.16
A6: SMART COFFEE molido 210g | B6: F1 | C6: 1 | D6: 19 | E6: 5 | F6: =D6*Parametros!$B$2 | G6: =E6*Parametros!$B$2 | H6: 0.22 | I6: 0
A7: SMART COFFEE Nespresso x10 | B7: F1 | C7: 1 | D7: 15 | E7: 3.5 | F7: =D7*Parametros!$B$2 | G7: =E7*Parametros!$B$2 | H7: 0.14 | I7: 0
A8: Greens + maca 300g | B8: F2 | C8: 4 | D8: 43 | E8: 6 | F8: =D8*Parametros!$B$2 | G8: =E8*Parametros!$B$2 | H8: 0.12 | I8: 0.15
A9: Creatina + maca + melena 300g | B9: F2 | C9: 4 | D9: 32 | E9: 4 | F9: =D9*Parametros!$B$2 | G9: =E9*Parametros!$B$2 | H9: 0.12 | I9: 0.15
A10: Healthy Aging +40 — cápsulas x60 | B10: F3 | C10: 7 | D10: 43 | E10: 4.5 | F10: =D10*Parametros!$B$2 | G10: =E10*Parametros!$B$2 | H10: 0.06 | I10: 0.1
A11: Suma mix (debe dar 100%) | H11: =SUM(H3:H10) | I11: =SUM(I3:I10)
A13: PVP promedio ponderado D2C (ARS) | D13: =SUMPRODUCT(F3:F10,H3:H10)
A14: Costo promedio ponderado D2C (ARS) | D14: =SUMPRODUCT(G3:G10,H3:H10)
A15: PVP promedio ponderado Dispro (ARS) | D15: =SUMPRODUCT(F3:F10,I3:I10)
A16: Costo promedio ponderado Dispro (ARS) | D16: =SUMPRODUCT(G3:G10,I3:I10)
A18: Nota: el mix es de régimen (todo lanzado). PVP Nespresso y costos = draft 18/7 [SUPUESTO hasta cotización PGN]. Cafés fuera del canal Dispro (mix 0%) — editable.

Sheet Supuestos
A1: SUPUESTOS OPERATIVOS
A2: MOTOR D2C
A3: AOV D2C (ARS, sin IVA) | B3: 110000 | D3: [HISTÓRICO DB] $107.788 en 2026, $90.078 en 2025. ~2,4 unidades/orden.
A4: CAC (USD por cliente nuevo) | B4: 10 | D4: [BENCHMARK AR] suplementos 8-15 USD. Sin histórico: venta fue 99% orgánica.
A5: Órdenes orgánicas mes 1 | B5: 55 | D5: [HISTÓRICO DB] ~53 órdenes/mes actuales sin pauta (2026).
A6: Crecimiento orgánico (%/mes) | B6: 0.03 | D6: [SUPUESTO] contenido founder-led + relanzamiento.
A7: % de nuevos que se vuelven repetidores | B7: 0.29 | D7: [HISTÓRICO DB] 1.223 de 4.209 clientes compraron 2+ veces.
A8: Compras/mes por repetidor activo | B8: 0.28 | D8: [HISTÓRICO DB] 107 días promedio entre compras (30/107).
A9: Churn mensual de repetidores | B9: 0.07 | D9: [DERIVADO] repetidores promedian 4 compras → vida ~14 meses.
A10: Mix D2C — Shopify | B10: 0.6 | D10: [A DEFINIR] (resp. 13: canales separados).
A11: Mix D2C — MercadoLibre | B11: 0.25 | D11: [A DEFINIR]
A12: Mix D2C — WhatsApp | B12: 0.15 | D12: [A DEFINIR]
A13: CANAL DISPROPHARMA
A14: Carga inicial (unidades por punto) | B14: 6 | D14: [A DEFINIR con Dispro] (resp. 21).
A15: Sell-out (unid/punto/mes) | B15: 3.5 | D15: [BENCHMARK AR] suplemento nuevo en farmacia rota 2-6 u/mes.
A16: % de puntos que reponen | B16: 0.8 | D16: [SUPUESTO] no todos los puntos rotan.
A18: MOQ reposición cápsulas (frascos) | B18: 2000 | D18: [SUPUESTO MERCADO] informativo — no entra en fórmulas.
A19: Lead time reposición (días) | B19: 60 | D19: [SUPUESTO MERCADO] informativo — cubierto por buffer inventario 30%.

Sheet Motor_D2C
B1: MOTOR D2C (Shopify + MercadoLibre + WhatsApp)
B2: Mes → | C2: 1 | D2: 2 | E2: 3 | F2: 4 | G2: 5 | H2: 6 | I2: 7 | J2: 8 | K2: 9 | L2: 10 | M2: 11 | N2: 12 | O2: 13 | P2: 14 | Q2: 15 | R2: 16 | S2: 17 | T2: 18 | U2: 19 | V2: 20 | W2: 21 | X2: 22 | Y2: 23 | Z2: 24
B3: Inversión Ads (USD) [EDITABLE] | C3: 1000 | D3: 1000 | E3: 1000 | F3: 1000 | G3: 1000 | H3: 1000 | I3: 1000 | J3: 1000 | K3: 1000 | L3: 1000 | M3: 1000 | N3: 1000 | O3: 1000 | P3: 1000 | Q3: 1000 | R3: 1000 | S3: 1000 | T3: 1000 | U3: 1000 | V3: 1000 | W3: 1000 | X3: 1000 | Y3: 1000 | Z3: 1000
B4: Inversión Ads (ARS) | C4: =C3*Parametros!$B$2 | D4: =D3*Parametros!$B$2 | E4: =E3*Parametros!$B$2 | F4: =F3*Parametros!$B$2 | G4: =G3*Parametros!$B$2 | H4: =H3*Parametros!$B$2 | I4: =I3*Parametros!$B$2 | J4: =J3*Parametros!$B$2 | ... Z4: =Z3*Parametros!$B$2
B5: Clientes nuevos por ads | C5: =(C3/Supuestos!$B$4)*Parametros!$B$24 | D5: =(D3/Supuestos!$B$4)*Parametros!$B$24 | E5: =(E3/Supuestos!$B$4)*Parametros!$B$24 | F5: =(F3/Supuestos!$B$4)*Parametros!$B$24 | G5: =(G3/Supuestos!$B$4)*Parametros!$B$24 | H5: =(H3/Supuestos!$B$4)*Parametros!$B$24 | I5: =(I3/Supuestos!$B$4)*Parametros!$B$24 | J5: =(J3/Supuestos!$B$4)*Parametros!$B$24 | ... Z5: =(Z3/Supuestos!$B$4)*Parametros!$B$24
B6: Órdenes orgánicas | C6: =Supuestos!$B$5*(1+Supuestos!$B$6)^(C2-1)*Parametros!$B$24 | D6: =Supuestos!$B$5*(1+Supuestos!$B$6)^(D2-1)*Parametros!$B$24 | E6: =Supuestos!$B$5*(1+Supuestos!$B$6)^(E2-1)*Parametros!$B$24 | F6: =Supuestos!$B$5*(1+Supuestos!$B$6)^(F2-1)*Parametros!$B$24 | G6: =Supuestos!$B$5*(1+Supuestos!$B$6)^(G2-1)*Parametros!$B$24 | H6: =Supuestos!$B$5*(1+Supuestos!$B$6)^(H2-1)*Parametros!$B$24 | I6: =Supuestos!$B$5*(1+Supuestos!$B$6)^(I2-1)*Parametros!$B$24 | J6: =Supuestos!$B$5*(1+Supuestos!$B$6)^(J2-1)*Parametros!$B$24 | ... Z6: =Supuestos!$B$5*(1+Supuestos!$B$6)^(Z2-1)*Parametros!$B$24
B7: Órdenes nuevas totales | C7: =C5+C6 | D7: =D5+D6 | E7: =E5+E6 | F7: =F5+F6 | G7: =G5+G6 | H7: =H5+H6 | I7: =I5+I6 | J7: =J5+J6 | ... Z7: =Z5+Z6
B8: Base de repetidores activos | C8: =C7*Supuestos!$B$7 | D8: =C8*(1-Supuestos!$B$9)+D7*Supuestos!$B$7 | E8: =D8*(1-Supuestos!$B$9)+E7*Supuestos!$B$7 | F8: =E8*(1-Supuestos!$B$9)+F7*Supuestos!$B$7 | G8: =F8*(1-Supuestos!$B$9)+G7*Supuestos!$B$7 | H8: =G8*(1-Supuestos!$B$9)+H7*Supuestos!$B$7 | I8: =H8*(1-Supuestos!$B$9)+I7*Supuestos!$B$7 | J8: =I8*(1-Supuestos!$B$9)+J7*Supuestos!$B$7 | K8: =J8*(1-Supuestos!$B$9)+K7*Supuestos!$B$7 | ... Z8: =Y8*(1-Supuestos!$B$9)+Z7*Supuestos!$B$7
B9: Órdenes de recompra | C9: =C8*Supuestos!$B$8 | D9: =D8*Supuestos!$B$8 | E9: =E8*Supuestos!$B$8 | F9: =F8*Supuestos!$B$8 | G9: =G8*Supuestos!$B$8 | H9: =H8*Supuestos!$B$8 | I9: =I8*Supuestos!$B$8 | J9: =J8*Supuestos!$B$8 | ... Z9: =Z8*Supuestos!$B$8
B10: Órdenes totales | C10: =C7+C9 | D10: =D7+D9 | E10: =E7+E9 | F10: =F7+F9 | G10: =G7+G9 | H10: =H7+H9 | I10: =I7+I9 | J10: =J7+J9 | ... Z10: =Z7+Z9
B11: Descuento promedio efectivo | C11: =Parametros!$B$19*Parametros!$B$18 | D11: =Parametros!$B$19*Parametros!$B$18 | E11: =Parametros!$B$19*Parametros!$B$18 | F11: =Parametros!$B$19*Parametros!$B$18 | G11: =Parametros!$B$19*Parametros!$B$18 | H11: =Parametros!$B$19*Parametros!$B$18 | I11: =Parametros!$B$19*Parametros!$B$18 | J11: =Parametros!$B$19*Parametros!$B$18 | ... Z11: =Parametros!$B$19*Parametros!$B$18
B12: REVENUE D2C (ARS) | C12: =C10*Supuestos!$B$3*(1-C11) | D12: =D10*Supuestos!$B$3*(1-D11) | E12: =E10*Supuestos!$B$3*(1-E11) | F12: =F10*Supuestos!$B$3*(1-F11) | G12: =G10*Supuestos!$B$3*(1-G11) | H12: =H10*Supuestos!$B$3*(1-H11) | I12: =I10*Supuestos!$B$3*(1-I11) | J12: =J10*Supuestos!$B$3*(1-J11) | ... Z12: =Z10*Supuestos!$B$3*(1-Z11)
B13: Unidades vendidas | C13: =C10*(Supuestos!$B$3/Productos!$D$13) | D13: =D10*(Supuestos!$B$3/Productos!$D$13) | E13: =E10*(Supuestos!$B$3/Productos!$D$13) | F13: =F10*(Supuestos!$B$3/Productos!$D$13) | G13: =G10*(Supuestos!$B$3/Productos!$D$13) | H13: =H10*(Supuestos!$B$3/Productos!$D$13) | I13: =I10*(Supuestos!$B$3/Productos!$D$13) | J13: =J10*(Supuestos!$B$3/Productos!$D$13) | ... Z13: =Z10*(Supuestos!$B$3/Productos!$D$13)
B14: COGS D2C (ARS) | C14: =C13*Productos!$D$14 | D14: =D13*Productos!$D$14 | E14: =E13*Productos!$D$14 | F14: =F13*Productos!$D$14 | G14: =G13*Productos!$D$14 | H14: =H13*Productos!$D$14 | I14: =I13*Productos!$D$14 | J14: =J13*Productos!$D$14 | ... Z14: =Z13*Productos!$D$14
B15: Comisiones de canal (ARS) | C15: =C12*(Supuestos!$B$10*Parametros!$B$14+Supuestos!$B$11*Parametros!$B$15+Supuestos!$B$12*Parametros!$B$17) | D15: =D12*(Supuestos!$B$10*Parametros!$B$14+Supuestos!$B$11*Parametros!$B$15+Supuestos!$B$12*Parametros!$B$17) | E15: =E12*(Supuestos!$B$10*Parametros!$B$14+Supuestos!$B$11*Parametros!$B$15+Supuestos!$B$12*Parametros!$B$17) | F15: =F12*(Supuestos!$B$10*Parametros!$B$14+Supuestos!$B$11*Parametros!$B$15+Supuestos!$B$12*Parametros!$B$17) | G15: =G12*(Supuestos!$B$10*Parametros!$B$14+Supuestos!$B$11*Parametros!$B$15+Supuestos!$B$12*Parametros!$B$17) | H15: =H12*(Supuestos!$B$10*Parametros!$B$14+Supuestos!$B$11*Parametros!$B$15+Supuestos!$B$12*Parametros!$B$17) | I15: =I12*(Supuestos!$B$10*Parametros!$B$14+Supuestos!$B$11*Parametros!$B$15+Supuestos!$B$12*Parametros!$B$17) | J15: =J12*(Supuestos!$B$10*Parametros!$B$14+Supuestos!$B$11*Parametros!$B$15+Supuestos!$B$12*Parametros!$B$17) | ... Z15: =Z12*(Supuestos!$B$10*Parametros!$B$14+Supuestos!$B$11*Parametros!$B$15+Supuestos!$B$12*Parametros!$B$17)
B16: Envíos MeLi (ARS) | C16: =C10*Supuestos!$B$11*Parametros!$B$16 | D16: =D10*Supuestos!$B$11*Parametros!$B$16 | E16: =E10*Supuestos!$B$11*Parametros!$B$16 | F16: =F10*Supuestos!$B$11*Parametros!$B$16 | G16: =G10*Supuestos!$B$11*Parametros!$B$16 | H16: =H10*Supuestos!$B$11*Parametros!$B$16 | I16: =I10*Supuestos!$B$11*Parametros!$B$16 | J16: =J10*Supuestos!$B$11*Parametros!$B$16 | ... Z16: =Z10*Supuestos!$B$11*Parametros!$B$16
B17: Fulfillment + envíos D2C (ARS) | C17: =C10*(Parametros!$B$12+Parametros!$B$13) | D17: =D10*(Parametros!$B$12+Parametros!$B$13) | E17: =E10*(Parametros!$B$12+Parametros!$B$13) | F17: =F10*(Parametros!$B$12+Parametros!$B$13) | G17: =G10*(Parametros!$B$12+Parametros!$B$13) | H17: =H10*(Parametros!$B$12+Parametros!$B$13) | I17: =I10*(Parametros!$B$12+Parametros!$B$13) | J17: =J10*(Parametros!$B$12+Parametros!$B$13) | ... Z17: =Z10*(Parametros!$B$12+Parametros!$B$13)
B18: CONTRIBUCIÓN D2C (ARS) | C18: =C12-C14-C15-C16-C17 | D18: =D12-D14-D15-D16-D17 | E18: =E12-E14-E15-E16-E17 | F18: =F12-F14-F15-F16-F17 | G18: =G12-G14-G15-G16-G17 | H18: =H12-H14-H15-H16-H17 | I18: =I12-I14-I15-I16-I17 | J18: =J12-J14-J15-J16-J17 | ... Z18: =Z12-Z14-Z15-Z16-Z17
B20: Ads: default USD 1.000/mes plano (resp. 10) — ajustá mes a mes. La fila 5 usa el CAC de Supuestos. Contribución NO descuenta ads (van en PyL como marketing).

Sheet Motor_Dispro
B1: MOTOR DISTRIBUIDOR (Dispropharma / Greenco) — compra en firme, cobro a 60 días
B2: Mes → | C2: 1 | D2: 2 | E2: 3 | F2: 4 | G2: 5 | H2: 6 | I2: 7 | J2: 8 | K2: 9 | L2: 10 | M2: 11 | N2: 12 | O2: 13 | P2: 14 | Q2: 15 | R2: 16 | S2: 17 | T2: 18 | U2: 19 | V2: 20 | W2: 21 | X2: 22 | Y2: 23 | Z2: 24
B3: Puntos de venta activos [EDITABLE] | C3: 0 | D3: 0 | E3: 40 | F3: 55 | G3: 70 | H3: 100 | I3: 115 | J3: 130 | K3: 160 | L3: 180 | M3: 200 | N3: 220 | O3: 235 | P3: 250 | Q3: 265 | R3: 280 | S3: 295 | T3: 310 | U3: 325 | V3: 340 | W3: 355 | X3: 370 | Y3: 385 | Z3: 400
B4: Puntos nuevos del mes | C4: =C3 | D4: =MAX(0,D3-C3) | E4: =MAX(0,E3-D3) | F4: =MAX(0,F3-E3) | G4: =MAX(0,G3-F3) | H4: =MAX(0,H3-G3) | I4: =MAX(0,I3-H3) | J4: =MAX(0,J3-I3) | K4: =MAX(0,K3-J3) | ... Z4: =MAX(0,Z3-Y3)
B5: Unidades sell-in inicial | C5: =C4*Supuestos!$B$14 | D5: =D4*Supuestos!$B$14 | E5: =E4*Supuestos!$B$14 | F5: =F4*Supuestos!$B$14 | G5: =G4*Supuestos!$B$14 | H5: =H4*Supuestos!$B$14 | I5: =I4*Supuestos!$B$14 | J5: =J4*Supuestos!$B$14 | ... Z5: =Z4*Supuestos!$B$14
B6: Unidades sell-out (reposición) | C6: =0 | D6: =C3*Supuestos!$B$15*Supuestos!$B$16*Parametros!$B$24 | E6: =D3*Supuestos!$B$15*Supuestos!$B$16*Parametros!$B$24 | F6: =E3*Supuestos!$B$15*Supuestos!$B$16*Parametros!$B$24 | G6: =F3*Supuestos!$B$15*Supuestos!$B$16*Parametros!$B$24 | H6: =G3*Supuestos!$B$15*Supuestos!$B$16*Parametros!$B$24 | I6: =H3*Supuestos!$B$15*Supuestos!$B$16*Parametros!$B$24 | J6: =I3*Supuestos!$B$15*Supuestos!$B$16*Parametros!$B$24 | K6: =J3*Supuestos!$B$15*Supuestos!$B$16*Parametros!$B$24 | ... Z6: =Y3*Supuestos!$B$15*Supuestos!$B$16*Parametros!$B$24
B7: Unidades totales | C7: =C5+C6 | D7: =D5+D6 | E7: =E5+E6 | F7: =F5+F6 | G7: =G5+G6 | H7: =H5+H6 | I7: =I5+I6 | J7: =J5+J6 | ... Z7: =Z5+Z6
B8: REVENUE DISPRO (ARS, neto 60% PVP) | C8: =C7*Productos!$D$15*(1-Parametros!$B$20) | D8: =D7*Productos!$D$15*(1-Parametros!$B$20) | E8: =E7*Productos!$D$15*(1-Parametros!$B$20) | F8: =F7*Productos!$D$15*(1-Parametros!$B$20) | G8: =G7*Productos!$D$15*(1-Parametros!$B$20) | H8: =H7*Productos!$D$15*(1-Parametros!$B$20) | I8: =I7*Productos!$D$15*(1-Parametros!$B$20) | J8: =J7*Productos!$D$15*(1-Parametros!$B$20) | ... Z8: =Z7*Productos!$D$15*(1-Parametros!$B$20)
B9: COGS Dispro (ARS) | C9: =C7*Productos!$D$16 | D9: =D7*Productos!$D$16 | E9: =E7*Productos!$D$16 | F9: =F7*Productos!$D$16 | G9: =G7*Productos!$D$16 | H9: =H7*Productos!$D$16 | I9: =I7*Productos!$D$16 | J9: =J7*Productos!$D$16 | ... Z9: =Z7*Productos!$D$16
B10: CONTRIBUCIÓN DISPRO (ARS) | C10: =C8-C9 | D10: =D8-D9 | E10: =E8-E9 | F10: =F8-F9 | G10: =G8-G9 | H10: =H8-H9 | I10: =I8-I9 | J10: =J8-J9 | ... Z10: =Z8-Z9
B11: Cobro del mes (ARS, +60 días) | C11: =0 | D11: =0 | E11: =C8 | F11: =D8 | G11: =E8 | H11: =F8 | I11: =G8 | J11: =H8 | K11: =I8 | L11: =J8 | ... Z11: =X8
B13: Ramp de puntos [A DEFINIR con Dispro]: propuesta 40 puntos en mes 3 → 220 en mes 12 → 400 en mes 24. Solo suplementos (cafés mix 0% en Productos). Sell-in inicial se factura al activar el punto.

Sheet PyL
B1: P&L MENSUAL (ARS, sin IVA) — EBITDA pre-impuestos
B2: Mes → | C2: 1 | D2: 2 | E2: 3 | F2: 4 | G2: 5 | H2: 6 | I2: 7 | J2: 8 | K2: 9 | L2: 10 | M2: 11 | N2: 12 | O2: 13 | P2: 14 | Q2: 15 | R2: 16 | S2: 17 | T2: 18 | U2: 19 | V2: 20 | W2: 21 | X2: 22 | Y2: 23 | Z2: 24 | AB2: AÑO 1 | AC2: AÑO 2
B3: Revenue D2C | C3: =Motor_D2C!C12 | D3: =Motor_D2C!D12 | E3: =Motor_D2C!E12 | F3: =Motor_D2C!F12 | G3: =Motor_D2C!G12 | H3: =Motor_D2C!H12 | I3: =Motor_D2C!I12 | J3: =Motor_D2C!J12 | ... Z3: =Motor_D2C!Z12 | AB3: =SUM(C3:N3) | AC3: =SUM(O3:Z3)
B4: Revenue Distribuidor | C4: =Motor_Dispro!C8 | D4: =Motor_Dispro!D8 | E4: =Motor_Dispro!E8 | F4: =Motor_Dispro!F8 | G4: =Motor_Dispro!G8 | H4: =Motor_Dispro!H8 | I4: =Motor_Dispro!I8 | J4: =Motor_Dispro!J8 | ... Z4: =Motor_Dispro!Z8 | AB4: =SUM(C4:N4) | AC4: =SUM(O4:Z4)
B5: REVENUE TOTAL | C5: =C3+C4 | D5: =D3+D4 | E5: =E3+E4 | F5: =F3+F4 | G5: =G3+G4 | H5: =H3+H4 | I5: =I3+I4 | J5: =J3+J4 | ... Z5: =Z3+Z4 | AB5: =SUM(C5:N5) | AC5: =SUM(O5:Z5)
B6: COGS total | C6: =Motor_D2C!C14+Motor_Dispro!C9 | D6: =Motor_D2C!D14+Motor_Dispro!D9 | E6: =Motor_D2C!E14+Motor_Dispro!E9 | F6: =Motor_D2C!F14+Motor_Dispro!F9 | G6: =Motor_D2C!G14+Motor_Dispro!G9 | H6: =Motor_D2C!H14+Motor_Dispro!H9 | I6: =Motor_D2C!I14+Motor_Dispro!I9 | J6: =Motor_D2C!J14+Motor_Dispro!J9 | ... Z6: =Motor_D2C!Z14+Motor_Dispro!Z9 | AB6: =SUM(C6:N6) | AC6: =SUM(O6:Z6)
B7: COGS cubierto por in-kind PGN | C7: =MIN(C6,Parametros!$B$30*Parametros!$B$2) | D7: =MIN(D6,MAX(0,Parametros!$B$30*Parametros!$B$2-SUM($C$7:C7))) | E7: =MIN(E6,MAX(0,Parametros!$B$30*Parametros!$B$2-SUM($C$7:D7))) | F7: =MIN(F6,MAX(0,Parametros!$B$30*Parametros!$B$2-SUM($C$7:E7))) | G7: =MIN(G6,MAX(0,Parametros!$B$30*Parametros!$B$2-SUM($C$7:F7))) | H7: =MIN(H6,MAX(0,Parametros!$B$30*Parametros!$B$2-SUM($C$7:G7))) | I7: =MIN(I6,MAX(0,Parametros!$B$30*Parametros!$B$2-SUM($C$7:H7))) | J7: =MIN(J6,MAX(0,Parametros!$B$30*Parametros!$B$2-SUM($C$7:I7))) | K7: =MIN(K6,MAX(0,Parametros!$B$30*Parametros!$B$2-SUM($C$7:J7))) | ... Z7: =MIN(Z6,MAX(0,Parametros!$B$30*Parametros!$B$2-SUM($C$7:Y7))) | AB7: =SUM(C7:N7) | AC7: =SUM(O7:Z7)
B8: COGS cash | C8: =C6-C7 | D8: =D6-D7 | E8: =E6-E7 | F8: =F6-F7 | G8: =G6-G7 | H8: =H6-H7 | I8: =I6-I7 | J8: =J6-J7 | ... Z8: =Z6-Z7 | AB8: =SUM(C8:N8) | AC8: =SUM(O8:Z8)
B9: MARGEN BRUTO | C9: =C5-C6 | D9: =D5-D6 | E9: =E5-E6 | F9: =F5-F6 | G9: =G5-G6 | H9: =H5-H6 | I9: =I5-I6 | J9: =J5-J6 | ... Z9: =Z5-Z6 | AB9: =SUM(C9:N9) | AC9: =SUM(O9:Z9)
B10: Variables de canal (comis.+envíos+fulf.) | C10: =Motor_D2C!C15+Motor_D2C!C16+Motor_D2C!C17 | D10: =Motor_D2C!D15+Motor_D2C!D16+Motor_D2C!D17 | E10: =Motor_D2C!E15+Motor_D2C!E16+Motor_D2C!E17 | F10: =Motor_D2C!F15+Motor_D2C!F16+Motor_D2C!F17 | G10: =Motor_D2C!G15+Motor_D2C!G16+Motor_D2C!G17 | H10: =Motor_D2C!H15+Motor_D2C!H16+Motor_D2C!H17 | I10: =Motor_D2C!I15+Motor_D2C!I16+Motor_D2C!I17 | J10: =Motor_D2C!J15+Motor_D2C!J16+Motor_D2C!J17 | ... Z10: =Motor_D2C!Z15+Motor_D2C!Z16+Motor_D2C!Z17 | AB10: =SUM(C10:N10) | AC10: =SUM(O10:Z10)
B11: Marketing (ads) | C11: =Motor_D2C!C4 | D11: =Motor_D2C!D4 | E11: =Motor_D2C!E4 | F11: =Motor_D2C!F4 | G11: =Motor_D2C!G4 | H11: =Motor_D2C!H4 | I11: =Motor_D2C!I4 | J11: =Motor_D2C!J4 | ... Z11: =Motor_D2C!Z4 | AB11: =SUM(C11:N11) | AC11: =SUM(O11:Z11)
B12: Contenido terciarizado | C12: =Parametros!$B$6*Parametros!$B$2 | D12: =Parametros!$B$6*Parametros!$B$2 | E12: =Parametros!$B$6*Parametros!$B$2 | F12: =Parametros!$B$6*Parametros!$B$2 | G12: =Parametros!$B$6*Parametros!$B$2 | H12: =Parametros!$B$6*Parametros!$B$2 | I12: =Parametros!$B$6*Parametros!$B$2 | J12: =Parametros!$B$6*Parametros!$B$2 | ... Z12: =Parametros!$B$6*Parametros!$B$2 | AB12: =SUM(C12:N12) | AC12: =SUM(O12:Z12)
B13: Sueldo fundador | C13: =Parametros!$B$4*Parametros!$B$2 | D13: =Parametros!$B$4*Parametros!$B$2 | E13: =Parametros!$B$4*Parametros!$B$2 | F13: =Parametros!$B$4*Parametros!$B$2 | G13: =Parametros!$B$4*Parametros!$B$2 | H13: =Parametros!$B$4*Parametros!$B$2 | I13: =Parametros!$B$4*Parametros!$B$2 | J13: =Parametros!$B$4*Parametros!$B$2 | ... Z13: =Parametros!$B$4*Parametros!$B$2 | AB13: =SUM(C13:N13) | AC13: =SUM(O13:Z13)
B14: CFO/admin fraccional | C14: =Parametros!$B$5 | D14: =Parametros!$B$5 | E14: =Parametros!$B$5 | F14: =Parametros!$B$5 | G14: =Parametros!$B$5 | H14: =Parametros!$B$5 | I14: =Parametros!$B$5 | J14: =Parametros!$B$5 | ... Z14: =Parametros!$B$5 | AB14: =SUM(C14:N14) | AC14: =SUM(O14:Z14)
B15: Otros fijos (contab+leg+seg+dep+tech) | C15: =Parametros!$B$7+Parametros!$B$8+Parametros!$B$9+Parametros!$B$10+Parametros!$B$11*Parametros!$B$2 | D15: =Parametros!$B$7+Parametros!$B$8+Parametros!$B$9+Parametros!$B$10+Parametros!$B$11*Parametros!$B$2 | E15: =Parametros!$B$7+Parametros!$B$8+Parametros!$B$9+Parametros!$B$10+Parametros!$B$11*Parametros!$B$2 | F15: =Parametros!$B$7+Parametros!$B$8+Parametros!$B$9+Parametros!$B$10+Parametros!$B$11*Parametros!$B$2 | G15: =Parametros!$B$7+Parametros!$B$8+Parametros!$B$9+Parametros!$B$10+Parametros!$B$11*Parametros!$B$2 | H15: =Parametros!$B$7+Parametros!$B$8+Parametros!$B$9+Parametros!$B$10+Parametros!$B$11*Parametros!$B$2 | I15: =Parametros!$B$7+Parametros!$B$8+Parametros!$B$9+Parametros!$B$10+Parametros!$B$11*Parametros!$B$2 | J15: =Parametros!$B$7+Parametros!$B$8+Parametros!$B$9+Parametros!$B$10+Parametros!$B$11*Parametros!$B$2 | ... Z15: =Parametros!$B$7+Parametros!$B$8+Parametros!$B$9+Parametros!$B$10+Parametros!$B$11*Parametros!$B$2 | AB15: =SUM(C15:N15) | AC15: =SUM(O15:Z15)
B16: Gastos de lanzamiento (USD) [EDITABLE] | C16: 8000 | D16: 8000 | E16: 4000 | F16: 2000 | G16: 0 | H16: 2000 | I16: 0 | J16: 0 | K16: 0 | L16: 0 | M16: 0 | N16: 0 | O16: 0 | P16: 0 | Q16: 0 | R16: 0 | S16: 0 | T16: 0 | U16: 0 | V16: 0 | W16: 0 | X16: 0 | Y16: 0 | Z16: 0
B17: Gastos de lanzamiento (ARS) | C17: =C16*Parametros!$B$2 | D17: =D16*Parametros!$B$2 | E17: =E16*Parametros!$B$2 | F17: =F16*Parametros!$B$2 | G17: =G16*Parametros!$B$2 | H17: =H16*Parametros!$B$2 | I17: =I16*Parametros!$B$2 | J17: =J16*Parametros!$B$2 | ... Z17: =Z16*Parametros!$B$2 | AB17: =SUM(C17:N17) | AC17: =SUM(O17:Z17)
B18: IIBB | C18: =C5*Parametros!$B$22 | D18: =D5*Parametros!$B$22 | E18: =E5*Parametros!$B$22 | F18: =F5*Parametros!$B$22 | G18: =G5*Parametros!$B$22 | H18: =H5*Parametros!$B$22 | I18: =I5*Parametros!$B$22 | J18: =J5*Parametros!$B$22 | ... Z18: =Z5*Parametros!$B$22 | AB18: =SUM(C18:N18) | AC18: =SUM(O18:Z18)
B19: EBITDA | C19: =C9-C10-C11-C12-C13-C14-C15-C17-C18 | D19: =D9-D10-D11-D12-D13-D14-D15-D17-D18 | E19: =E9-E10-E11-E12-E13-E14-E15-E17-E18 | F19: =F9-F10-F11-F12-F13-F14-F15-F17-F18 | G19: =G9-G10-G11-G12-G13-G14-G15-G17-G18 | H19: =H9-H10-H11-H12-H13-H14-H15-H17-H18 | I19: =I9-I10-I11-I12-I13-I14-I15-I17-I18 | J19: =J9-J10-J11-J12-J13-J14-J15-J17-J18 | ... Z19: =Z9-Z10-Z11-Z12-Z13-Z14-Z15-Z17-Z18 | AB19: =SUM(C19:N19) | AC19: =SUM(O19:Z19)
B20: EBITDA acumulado | C20: =C19 | D20: =C20+D19 | E20: =D20+E19 | F20: =E20+F19 | G20: =F20+G19 | H20: =G20+H19 | I20: =H20+I19 | J20: =I20+J19 | K20: =J20+K19 | ... Z20: =Y20+Z19
B21: Margen EBITDA % | C21: =IF(C5=0,0,C19/C5) | D21: =IF(D5=0,0,D19/D5) | E21: =IF(E5=0,0,E19/E5) | F21: =IF(F5=0,0,F19/F5) | G21: =IF(G5=0,0,G19/G5) | H21: =IF(H5=0,0,H19/H5) | I21: =IF(I5=0,0,I19/I5) | J21: =IF(J5=0,0,J19/J5) | ... Z21: =IF(Z5=0,0,Z19/Z5) | AB21: =IF(AB5=0,0,AB19/AB5) | AC21: =IF(AC5=0,0,AC19/AC5)
B22: In-kind PGN restante (ARS) | C22: =MAX(0,Parametros!$B$30*Parametros!$B$2-SUM($C$7:C7)) | D22: =MAX(0,Parametros!$B$30*Parametros!$B$2-SUM($C$7:D7)) | E22: =MAX(0,Parametros!$B$30*Parametros!$B$2-SUM($C$7:E7)) | F22: =MAX(0,Parametros!$B$30*Parametros!$B$2-SUM($C$7:F7)) | G22: =MAX(0,Parametros!$B$30*Parametros!$B$2-SUM($C$7:G7)) | H22: =MAX(0,Parametros!$B$30*Parametros!$B$2-SUM($C$7:H7)) | I22: =MAX(0,Parametros!$B$30*Parametros!$B$2-SUM($C$7:I7)) | J22: =MAX(0,Parametros!$B$30*Parametros!$B$2-SUM($C$7:J7)) | ... Z22: =MAX(0,Parametros!$B$30*Parametros!$B$2-SUM($C$7:Z7))

Sheet Caja
B1: FLUJO DE CAJA MENSUAL (ARS) — cobro Dispro +60d · producción cash con buffer de inventario
B2: Mes → | C2: 1 | D2: 2 | E2: 3 | F2: 4 | G2: 5 | H2: 6 | I2: 7 | J2: 8 | K2: 9 | L2: 10 | M2: 11 | N2: 12 | O2: 13 | P2: 14 | Q2: 15 | R2: 16 | S2: 17 | T2: 18 | U2: 19 | V2: 20 | W2: 21 | X2: 22 | Y2: 23 | Z2: 24
B3: Aportes de capital cash | C3: =IF(C2=1,(Parametros!$B$26+Parametros!$B$27)*Parametros!$B$28*Parametros!$B$2,IF(C2=Parametros!$B$29,(Parametros!$B$26+Parametros!$B$27)*(1-Parametros!$B$28)*Parametros!$B$2,0)) | D3: =IF(D2=1,(Parametros!$B$26+Parametros!$B$27)*Parametros!$B$28*Parametros!$B$2,IF(D2=Parametros!$B$29,(Parametros!$B$26+Parametros!$B$27)*(1-Parametros!$B$28)*Parametros!$B$2,0)) | E3: =IF(E2=1,(Parametros!$B$26+Parametros!$B$27)*Parametros!$B$28*Parametros!$B$2,IF(E2=Parametros!$B$29,(Parametros!$B$26+Parametros!$B$27)*(1-Parametros!$B$28)*Parametros!$B$2,0)) | F3: =IF(F2=1,(Parametros!$B$26+Parametros!$B$27)*Parametros!$B$28*Parametros!$B$2,IF(F2=Parametros!$B$29,(Parametros!$B$26+Parametros!$B$27)*(1-Parametros!$B$28)*Parametros!$B$2,0)) | G3: =IF(G2=1,(Parametros!$B$26+Parametros!$B$27)*Parametros!$B$28*Parametros!$B$2,IF(G2=Parametros!$B$29,(Parametros!$B$26+Parametros!$B$27)*(1-Parametros!$B$28)*Parametros!$B$2,0)) | H3: =IF(H2=1,(Parametros!$B$26+Parametros!$B$27)*Parametros!$B$28*Parametros!$B$2,IF(H2=Parametros!$B$29,(Parametros!$B$26+Parametros!$B$27)*(1-Parametros!$B$28)*Parametros!$B$2,0)) | I3: =IF(I2=1,(Parametros!$B$26+Parametros!$B$27)*Parametros!$B$28*Parametros!$B$2,IF(I2=Parametros!$B$29,(Parametros!$B$26+Parametros!$B$27)*(1-Parametros!$B$28)*Parametros!$B$2,0)) | J3: =IF(J2=1,(Parametros!$B$26+Parametros!$B$27)*Parametros!$B$28*Parametros!$B$2,IF(J2=Parametros!$B$29,(Parametros!$B$26+Parametros!$B$27)*(1-Parametros!$B$28)*Parametros!$B$2,0)) | ... Z3: =IF(Z2=1,(Parametros!$B$26+Parametros!$B$27)*Parametros!$B$28*Parametros!$B$2,IF(Z2=Parametros!$B$29,(Parametros!$B$26+Parametros!$B$27)*(1-Parametros!$B$28)*Parametros!$B$2,0))
B4: Cobros D2C | C4: =PyL!C3 | D4: =PyL!D3 | E4: =PyL!E3 | F4: =PyL!F3 | G4: =PyL!G3 | H4: =PyL!H3 | I4: =PyL!I3 | J4: =PyL!J3 | ... Z4: =PyL!Z3
B5: Cobros Distribuidor (+60d) | C5: =Motor_Dispro!C11 | D5: =Motor_Dispro!D11 | E5: =Motor_Dispro!E11 | F5: =Motor_Dispro!F11 | G5: =Motor_Dispro!G11 | H5: =Motor_Dispro!H11 | I5: =Motor_Dispro!I11 | J5: =Motor_Dispro!J11 | ... Z5: =Motor_Dispro!Z11
B6: TOTAL INGRESOS | C6: =C3+C4+C5 | D6: =D3+D4+D5 | E6: =E3+E4+E5 | F6: =F3+F4+F5 | G6: =G3+G4+G5 | H6: =H3+H4+H5 | I6: =I3+I4+I5 | J6: =J3+J4+J5 | ... Z6: =Z3+Z4+Z5
B7: Producción cash (COGS cash × 1+buffer) | C7: =PyL!C8*(1+Parametros!$B$23) | D7: =PyL!D8*(1+Parametros!$B$23) | E7: =PyL!E8*(1+Parametros!$B$23) | F7: =PyL!F8*(1+Parametros!$B$23) | G7: =PyL!G8*(1+Parametros!$B$23) | H7: =PyL!H8*(1+Parametros!$B$23) | I7: =PyL!I8*(1+Parametros!$B$23) | J7: =PyL!J8*(1+Parametros!$B$23) | ... Z7: =PyL!Z8*(1+Parametros!$B$23)
B8: Variables de canal | C8: =PyL!C10 | D8: =PyL!D10 | E8: =PyL!E10 | F8: =PyL!F10 | G8: =PyL!G10 | H8: =PyL!H10 | I8: =PyL!I10 | J8: =PyL!J10 | ... Z8: =PyL!Z10
B9: Marketing (ads) | C9: =PyL!C11 | D9: =PyL!D11 | E9: =PyL!E11 | F9: =PyL!F11 | G9: =PyL!G11 | H9: =PyL!H11 | I9: =PyL!I11 | J9: =PyL!J11 | ... Z9: =PyL!Z11
B10: Fijos totales | C10: =PyL!C12+PyL!C13+PyL!C14+PyL!C15 | D10: =PyL!D12+PyL!D13+PyL!D14+PyL!D15 | E10: =PyL!E12+PyL!E13+PyL!E14+PyL!E15 | F10: =PyL!F12+PyL!F13+PyL!F14+PyL!F15 | G10: =PyL!G12+PyL!G13+PyL!G14+PyL!G15 | H10: =PyL!H12+PyL!H13+PyL!H14+PyL!H15 | I10: =PyL!I12+PyL!I13+PyL!I14+PyL!I15 | J10: =PyL!J12+PyL!J13+PyL!J14+PyL!J15 | ... Z10: =PyL!Z12+PyL!Z13+PyL!Z14+PyL!Z15
B11: Gastos de lanzamiento | C11: =PyL!C17 | D11: =PyL!D17 | E11: =PyL!E17 | F11: =PyL!F17 | G11: =PyL!G17 | H11: =PyL!H17 | I11: =PyL!I17 | J11: =PyL!J17 | ... Z11: =PyL!Z17
B12: IIBB | C12: =PyL!C18 | D12: =PyL!D18 | E12: =PyL!E18 | F12: =PyL!F18 | G12: =PyL!G18 | H12: =PyL!H18 | I12: =PyL!I18 | J12: =PyL!J18 | ... Z12: =PyL!Z18
B13: TOTAL EGRESOS | C13: =C7+C8+C9+C10+C11+C12 | D13: =D7+D8+D9+D10+D11+D12 | E13: =E7+E8+E9+E10+E11+E12 | F13: =F7+F8+F9+F10+F11+F12 | G13: =G7+G8+G9+G10+G11+G12 | H13: =H7+H8+H9+H10+H11+H12 | I13: =I7+I8+I9+I10+I11+I12 | J13: =J7+J8+J9+J10+J11+J12 | ... Z13: =Z7+Z8+Z9+Z10+Z11+Z12
B14: FLUJO DEL MES | C14: =C6-C13 | D14: =D6-D13 | E14: =E6-E13 | F14: =F6-F13 | G14: =G6-G13 | H14: =H6-H13 | I14: =I6-I13 | J14: =J6-J13 | ... Z14: =Z6-Z13
B15: CAJA ACUMULADA | C15: =C14 | D15: =C15+D14 | E15: =D15+E14 | F15: =E15+F14 | G15: =F15+G14 | H15: =G15+H14 | I15: =H15+I14 | J15: =I15+J14 | K15: =J15+K14 | ... Z15: =Y15+Z14
B16: Flujo operativo (sin aportes) | C16: =C14-C3 | D16: =D14-D3 | E16: =E14-E3 | F16: =F14-F3 | G16: =G14-G3 | H16: =H14-H3 | I16: =I14-I3 | J16: =J14-J3 | ... Z16: =Z14-Z3
B17: Operativo acumulado (recuperación del capital) | C17: =C16 | D17: =C17+D16 | E17: =D17+E16 | F17: =E17+F16 | G17: =F17+G16 | H17: =G17+H16 | I17: =H17+I16 | J17: =I17+J16 | K17: =J17+K16 | ... Z17: =Y17+Z16
B19: Cobros D2C asumidos al contado (MeLi libera ~14 días — simplificado). Si CAJA ACUMULADA da negativa en algún mes: falta capital o hay que adelantar el Tramo 2.

Sheet Anios_3_5
A1: AÑOS 3-5 (anual, ARS) — growth sobre Año 2
B2: Año 2 (base) | C2: Año 3 | D2: Año 4 | E2: Año 5
A3: Crecimiento revenue vs año anterior | C3: 0.6 | D3: 0.45 | E3: 0.35
A4: REVENUE (ARS) | B4: =PyL!AC5 | C4: =B4*(1+C3) | D4: =C4*(1+D3) | E4: =D4*(1+E3)
A5: Margen EBITDA % | B5: =PyL!AC21 | C5: 0.14 | D5: 0.17 | E5: 0.2
A6: EBITDA (ARS) | B6: =PyL!AC19 | C6: =C4*C5 | D6: =D4*D5 | E6: =E4*E5
A7: Revenue (USD) | B7: =B4/Parametros!$B$2 | C7: =C4/Parametros!$B$2 | D7: =D4/Parametros!$B$2 | E7: =E4/Parametros!$B$2
A8: EBITDA (USD) | B8: =B6/Parametros!$B$2 | C8: =C6/Parametros!$B$2 | D8: =D6/Parametros!$B$2 | E8: =E6/Parametros!$B$2
A10: Múltiplo de valuación (x EBITDA) | B10: 6
A11: VALOR EMPRESA AÑO 5 (USD) | B11: =E8*B10
A13: Growth defaults [SUPUESTO]: +60% / +45% / +35% con márgenes 14% / 17% / 20%. Editables. CPG en relanzamiento con canal en expansión.

Sheet Umbrales
A1: UMBRALES Y SEMÁFOROS
A3: 1. NEGOCIO — Breakeven operativo (primer mes EBITDA > 0) | B3: =IF(COUNTIF(PyL!C19:Z19,">0")=0,"no en 24m",25-COUNTIF(PyL!C19:Z19,">0"))
A4: Caja mínima del período (ARS) — si es negativa falta capital | B4: =MIN(Caja!C15:Z15)
A6: 2. PISO — Recuperar el capital cash (mes en que el flujo operativo acumulado ≥ −aportes... ver nota)
A7: Aportes cash totales (ARS) | B7: =(Parametros!$B$26+Parametros!$B$27)*Parametros!$B$2
A8: Primer mes con operativo acumulado ≥ 0 (el negocio devolvió lo consumido) | B8: =IF(COUNTIF(Caja!C17:Z17,">=0")=0,"no en 24m",25-COUNTIF(Caja!C17:Z17,">=0"))
A9: ¿PISO cumplido? (≤ 12 meses) | B9: =IF(ISNUMBER(B8),IF(B8<=12,"PASS","FAIL"),"FAIL")
A11: 3. ANDRÉS — Umbral personal USD 10.000/mes (sueldo + 55% del EBITDA)
A12: EBITDA mensual necesario (ARS) = (10.000 − sueldo USD) × TC ÷ 55% | B12: =(10000-Parametros!$B$4)*Parametros!$B$2/0.55
A13: Primer mes que lo cruza | B13: =IF(COUNTIF(PyL!C19:Z19,">="&B12)=0,"no en 24m",25-COUNTIF(PyL!C19:Z19,">="&B12))
A14: Nota: dividendo real depende de caja y reinversión — este umbral es de capacidad, no de distribución.
A16: 4. SOCIOS — Retorno sobre aporte externo total (USD 184.000, 45% del equity)
A17: Escenario | B17: Múltiplo | C17: Valor empresa req. (USD) | D17: EBITDA Año 5 req. (USD) | E17: Ventas netas Año 5 req. (USD)
A18: Conservador | B18: 3 | C18: =(Parametros!$B$26+Parametros!$B$27+Parametros!$B$30)*B18/0.45 | D18: =C18/Anios_3_5!$B$10 | E18: =D18/0.20
A19: Intermedio | B19: 5 | C19: =(Parametros!$B$26+Parametros!$B$27+Parametros!$B$30)*B19/0.45 | D19: =C19/Anios_3_5!$B$10 | E19: =D19/0.20
A20: Optimista | B20: 10 | C20: =(Parametros!$B$26+Parametros!$B$27+Parametros!$B$30)*B20/0.45 | D20: =C20/Anios_3_5!$B$10 | E20: =D20/0.20
A22: Proyección actual Año 5 → EBITDA (USD) / Valor empresa (USD) | C22: =Anios_3_5!B11 | D22: =Anios_3_5!E8
A24: ESCENARIOS: poné el Multiplicador de demanda (Parametros!B24) en 0,70 = PISO · 1,00 = BASE · 1,30 = TECHO y mirá cómo cambian los semáforos.
A25: Ventas req. asume margen EBITDA 20% en año 5. El equity de socios (45%) y el cap table son la propuesta discutida el 19/7 — ajustar cuando se negocie.
